heroes091238912/__init__.py
heroes091238912/math.py
heroes091238912-0.0.1.dist-info/METADATA
heroes091238912-0.0.1.dist-info/WHEEL
heroes091238912-0.0.1.dist-info/top_level.txt
heroes091238912-0.0.1.dist-info/RECORD
